inkletter/__init__.py
inkletter/ast.py
inkletter/cli.py
inkletter/codeblock.py
inkletter/md_to_ast.py
inkletter/md_to_html.py
inkletter/md_to_mjml.py
inkletter/scope.py
inkletter/templates/preview.html
inkletter/visitors/__init__.py
inkletter/visitors/annotation.py
inkletter/visitors/codegen.py
inkletter/visitors/generic.py
inkletter/visitors/merger.py
inkletter/visitors/tree.py
inkletter-1.0.0.dist-info/licenses/LICENSE
inkletter-1.0.0.dist-info/METADATA
inkletter-1.0.0.dist-info/WHEEL
inkletter-1.0.0.dist-info/entry_points.txt
inkletter-1.0.0.dist-info/top_level.txt
inkletter-1.0.0.dist-info/RECORD
