Metadata-Version: 2.4
Name: inkletter
Version: 1.0.0
Summary: Markdown to MJML/HTML converter and previewer
Author-email: Laurent Pauloin <laurent@crococode.co>
Project-URL: Homepage, https://github.com/CrocoCode-co/Inkletter
Project-URL: Repository, https://github.com/CrocoCode-co/Inkletter
Project-URL: Issues, https://github.com/CrocoCode-co/Inkletter/issues
Requires-Python: >=3.8
License-File: LICENSE
Requires-Dist: click==8.2.1
Requires-Dist: jinja2==3.1.6
Requires-Dist: mistune==3.1.3
Requires-Dist: mjml-python==1.3.5
Dynamic: license-file
